[
  {
    "id": "519e8716-002b-4302-94e6-570239b76a91",
    "name": "Sample Company Ltd",
    "type": "company",
    "email": "info@samplecompany.com",
    "phone": "+1234567890",
    "address": null,
    "tax_id": null,
    "registration_number": null,
    "status": "active",
    "created_at": "2025-08-01T14:28:36.821487+00:00",
    "updated_at": "2025-08-01T14:28:36.821487+00:00"
  },
  {
    "id": "209a4aa8-8f9a-4979-8a75-da842406c6ed",
    "name": "Falcon Eye Modern Investments SPC",
    "type": "company",
    "email": null,
    "phone": null,
    "address": null,
    "tax_id": null,
    "registration_number": null,
    "status": "active",
    "created_at": "2025-08-01T15:33:40.25+00:00",
    "updated_at": "2025-08-01T15:33:40.25+00:00"
  },
  {
    "id": "3bf281e0-ed06-41c4-8fe3-65c674535b56",
    "name": "Falcon Eye Projects Management",
    "type": "company",
    "email": null,
    "phone": null,
    "address": null,
    "tax_id": null,
    "registration_number": null,
    "status": "active",
    "created_at": "2025-08-01T15:33:40.661+00:00",
    "updated_at": "2025-08-01T15:33:40.661+00:00"
  },
  {
    "id": "0c7ac1eb-5833-4dcb-bf5d-496330b9a6a4",
    "name": "Falcon Eye Al Khaleej",
    "type": "company",
    "email": null,
    "phone": null,
    "address": null,
    "tax_id": null,
    "registration_number": null,
    "status": "active",
    "created_at": "2025-08-01T15:33:41.049+00:00",
    "updated_at": "2025-08-01T15:33:41.049+00:00"
  },
  {
    "id": "8fdff458-2ca1-4cda-b823-2410d3f16db5",
    "name": "Tawreed International",
    "type": "company",
    "email": null,
    "phone": null,
    "address": null,
    "tax_id": null,
    "registration_number": null,
    "status": "active",
    "created_at": "2025-08-01T15:33:41.41+00:00",
    "updated_at": "2025-08-01T15:33:41.41+00:00"
  },
  {
    "id": "7a446233-1717-43b1-98a0-94d94dec4521",
    "name": "Falcon Eye Business and Promotion",
    "type": "company",
    "email": null,
    "phone": null,
    "address": null,
    "tax_id": null,
    "registration_number": null,
    "status": "active",
    "created_at": "2025-08-01T15:33:41.765+00:00",
    "updated_at": "2025-08-01T15:33:41.765+00:00"
  },
  {
    "id": "98b5f9da-6d4f-4b37-b444-64537892dd33",
    "name": "Blue Oasis Quality Services",
    "type": "company",
    "email": null,
    "phone": null,
    "address": null,
    "tax_id": null,
    "registration_number": null,
    "status": "active",
    "created_at": "2025-08-01T15:33:42.777+00:00",
    "updated_at": "2025-08-01T15:33:42.777+00:00"
  },
  {
    "id": "cf977959-6b48-40b4-9129-5f2d424db53c",
    "name": "Falcon Eye Management and Investment",
    "type": "company",
    "email": null,
    "phone": null,
    "address": null,
    "tax_id": null,
    "registration_number": null,
    "status": "active",
    "created_at": "2025-08-01T15:33:43.142+00:00",
    "updated_at": "2025-08-01T15:33:43.142+00:00"
  }
]